pygifconvt_sihyeon/__init__.py
pygifconvt_sihyeon/converter.py
pygifconvt_sihyeon-1.0.0.dist-info/LICENSE
pygifconvt_sihyeon-1.0.0.dist-info/METADATA
pygifconvt_sihyeon-1.0.0.dist-info/WHEEL
pygifconvt_sihyeon-1.0.0.dist-info/top_level.txt
pygifconvt_sihyeon-1.0.0.dist-info/RECORD
